entangle/__init__.py
entangle/client.py
entangle/entanglement.py
entangle/server.py
entangle_python-20201010.2.dist-info/LICENSE
entangle_python-20201010.2.dist-info/METADATA
entangle_python-20201010.2.dist-info/WHEEL
entangle_python-20201010.2.dist-info/top_level.txt
entangle_python-20201010.2.dist-info/RECORD
