Metadata-Version: 2.1
Name: entangle-python
Version: 20201010.2
Summary: Create an entanglement across network and even programming language.
Home-page: https://github.com/penguinmenac3/entangle-python
Author: Michael Fuerst
Author-email: mail@michaelfuerst.de
License: BSD
Download-URL: https://github.com/penguinmenac3/entangle-python/tarball/20201010.2
Platform: UNKNOWN
Classifier: Development Status :: 3 - Alpha
Classifier: Intended Audience :: Developers
Classifier: Programming Language :: Python
Requires-Dist: service-identity
Requires-Dist: autobahn[twisted]
Requires-Dist: bcrypt
